masster/__init__.py
masster/_version.py
masster/chromatogram.py
masster/constants.py
masster/exceptions.py
masster/logger.py
masster/spectrum.py
masster/data/libs/aa.json
masster/data/libs/ccm_nort.json
masster/data/libs/core.json
masster/data/libs/ecoli.json
masster/data/libs/hsapiens.json
masster/data/libs/name_translator.parquet
masster/data/libs/scerevisiae.json
masster/lib/__init__.py
masster/lib/lib.py
masster/sample/__init__.py
masster/sample/adducts.py
masster/sample/h5.py
masster/sample/helpers.py
masster/sample/id.py
masster/sample/importers.py
masster/sample/load.py
masster/sample/parameters.py
masster/sample/plot.py
masster/sample/processing.py
masster/sample/quant.py
masster/sample/sample.py
masster/sample/sample5_schema.json
masster/sample/save.py
masster/sample/sciex.py
masster/sample/sciex_v2.py
masster/sample/thermo.py
masster/sample/defaults/__init__.py
masster/sample/defaults/find_adducts_def.py
masster/sample/defaults/find_features_def.py
masster/sample/defaults/find_ms2_def.py
masster/sample/defaults/get_spectrum_def.py
masster/sample/defaults/sample_def.py
masster/study/__init__.py
masster/study/analysis.py
masster/study/export.py
masster/study/h5.py
masster/study/h5_v3.py
masster/study/helpers.py
masster/study/id.py
masster/study/importers.py
masster/study/load.py
masster/study/merge.py
masster/study/parameters.py
masster/study/plot.py
masster/study/processing.py
masster/study/samples.py
masster/study/save.py
masster/study/study.py
masster/study/study5_schema.json
masster/study/defaults/__init__.py
masster/study/defaults/align_def.py
masster/study/defaults/export_def.py
masster/study/defaults/fill_def.py
masster/study/defaults/find_consensus_def.py
masster/study/defaults/find_ms2_def.py
masster/study/defaults/identify_def.py
masster/study/defaults/integrate_chrom_def.py
masster/study/defaults/integrate_def.py
masster/study/defaults/merge_def.py
masster/study/defaults/study_def.py
masster/wizard/__init__.py
masster/wizard/wizard.py
masster-0.9.13.dist-info/METADATA
masster-0.9.13.dist-info/WHEEL
masster-0.9.13.dist-info/entry_points.txt
masster-0.9.13.dist-info/licenses/LICENSE
masster-0.9.13.dist-info/RECORD
