Metadata-Version: 2.4
Name: masster
Version: 0.9.13
Summary: Mass spectrometry data analysis package
Project-URL: homepage, https://github.com/zamboni-lab/masster
Project-URL: repository, https://github.com/zamboni-lab/masster
Project-URL: documentation, https://github.com/zamboni-lab/masster#readme
Project-URL: Third-Party Licenses, https://github.com/zamboni-lab/masster/blob/main/THIRD_PARTY_NOTICES.md
Author: Zamboni Lab, ETH Zurich
License:                     GNU AFFERO GENERAL PUBLIC LICENSE
License-File: LICENSE
Keywords: lc-ms,lc-msms,mass spectrometry,metabolomics
Classifier: Development Status :: 4 - Beta
Classifier: Intended Audience :: Science/Research
Classifier: License :: OSI Approved :: GNU Affero General Public License v3
Classifier: Natural Language :: English
Classifier: Operating System :: OS Independent
Classifier: Programming Language :: Python :: 3
Classifier: Programming Language :: Python :: 3 :: Only
Classifier: Programming Language :: Python :: 3.11
Classifier: Programming Language :: Python :: 3.12
Classifier: Programming Language :: Python :: 3.13
Classifier: Programming Language :: Python :: Implementation :: CPython
Classifier: Topic :: Scientific/Engineering
Classifier: Topic :: Scientific/Engineering :: Bio-Informatics
Classifier: Topic :: Scientific/Engineering :: Chemistry
Classifier: Topic :: Scientific/Engineering :: Information Analysis
Classifier: Typing :: Typed
Requires-Python: >=3.11
Requires-Dist: alpharaw>=0.4.8
Requires-Dist: bokeh>=3.7.3
Requires-Dist: cmap>=0.6.2
Requires-Dist: datashader>=0.18.1
Requires-Dist: h5py>=3.14.0
Requires-Dist: hdbscan>=0.8.40
Requires-Dist: holoviews>=1.21.0
Requires-Dist: hvplot>=0.11.3
Requires-Dist: ipykernel>=6.29.0
Requires-Dist: loguru>=0.7.3
Requires-Dist: matplotlib>=3.8.0
Requires-Dist: numba>=0.63
Requires-Dist: numpy>=2.0.0
Requires-Dist: openpyxl>=3.1.5
Requires-Dist: pandas>=2.2.0
Requires-Dist: panel>=1.7.0
Requires-Dist: polars<=1.34
Requires-Dist: pyopenms>=3.3.0
Requires-Dist: pythonnet>=3.0.0
Requires-Dist: scikit-learn>=1.7.1
Requires-Dist: scipy>=1.12.0
Requires-Dist: selenium>=4.39.0
Requires-Dist: tqdm>=4.65.0
Requires-Dist: umap-learn>=0.5.9.post2
Requires-Dist: uuid6>=2025.0.1
Requires-Dist: webdriver-manager>=4.0.2
Provides-Extra: dev
Requires-Dist: deptry>=0.24.0; extra == 'dev'
Requires-Dist: mypy>=1.0.0; extra == 'dev'
Requires-Dist: pytest-cov>=4.0.0; extra == 'dev'
Requires-Dist: pytest>=7.0.0; extra == 'dev'
Requires-Dist: ruff>=0.8.0; extra == 'dev'
Requires-Dist: twine>=5.0.0; extra == 'dev'
Provides-Extra: docs
Requires-Dist: myst-parser>=1.0.0; extra == 'docs'
Requires-Dist: sphinx-autobuild>=2021.3.14; extra == 'docs'
Requires-Dist: sphinx-markdown-builder>=0.6.9; extra == 'docs'
Requires-Dist: sphinx-rtd-theme>=1.2.0; extra == 'docs'
Requires-Dist: sphinx>=8.2.3; extra == 'docs'
Requires-Dist: sphinxcontrib-napoleon>=0.7.0; extra == 'docs'
